ypack/__init__.py
ypack/module_sample.py
ypack-0.1.0.dist-info/LICENSE
ypack-0.1.0.dist-info/METADATA
ypack-0.1.0.dist-info/WHEEL
ypack-0.1.0.dist-info/top_level.txt
ypack-0.1.0.dist-info/RECORD
