Metadata-Version: 1.1
Name: ypack
Version: 0.1.0
Summary: A example Python package
Home-page: https://github.com/YoussephAhmed/ypack
Author: Youssef Ahmed
Author-email: yousseffahmed@hotmail.com
License: BSD 2-clause
Platform: UNKNOWN
Classifier: Development Status :: 1 - Planning
Classifier: Intended Audience :: Science/Research
Classifier: License :: OSI Approved :: BSD License
Classifier: Operating System :: POSIX :: Linux
Classifier: Programming Language :: Python :: 2
Classifier: Programming Language :: Python :: 2.7
Classifier: Programming Language :: Python :: 3
Classifier: Programming Language :: Python :: 3.4
Classifier: Programming Language :: Python :: 3.5
